ai_unit_test/__init__.py
ai_unit_test/__main__.py
ai_unit_test/_version.py
ai_unit_test/cli.py
ai_unit_test/coverage_helper.py
ai_unit_test/file_helper.py
ai_unit_test/main.py
ai_unit_test/py.typed
ai_unit_test/core/__init__.py
ai_unit_test/core/cli_manager.py
ai_unit_test/core/exceptions.py
ai_unit_test/core/system_orchestrator.py
ai_unit_test/core/factories/__init__.py
ai_unit_test/core/factories/index_factory.py
ai_unit_test/core/factories/llm_factory.py
ai_unit_test/core/implementations/__init__.py
ai_unit_test/core/implementations/indexing/__init__.py
ai_unit_test/core/implementations/indexing/faiss_organizer.py
ai_unit_test/core/implementations/indexing/memory_organizer.py
ai_unit_test/core/implementations/indexing/sklearn_organizer.py
ai_unit_test/core/implementations/llm/__init__.py
ai_unit_test/core/implementations/llm/huggingface_connector.py
ai_unit_test/core/implementations/llm/mock_connector.py
ai_unit_test/core/implementations/llm/openai_connector.py
ai_unit_test/core/interfaces/__init__.py
ai_unit_test/core/interfaces/index_organizer.py
ai_unit_test/core/interfaces/llm_connector.py
ai_unit_test/services/__init__.py
ai_unit_test/services/base_service.py
ai_unit_test/services/configuration_service.py
ai_unit_test/services/orchestration_service.py
ai_unit_test/services/processing_service.py
aiunittest-0.0.7.dist-info/licenses/LICENSE
aiunittest-0.0.7.dist-info/METADATA
aiunittest-0.0.7.dist-info/WHEEL
aiunittest-0.0.7.dist-info/entry_points.txt
aiunittest-0.0.7.dist-info/top_level.txt
aiunittest-0.0.7.dist-info/RECORD
