Metadata-Version: 2.4
Name: AIUnitTest
Version: 0.0.7
Summary: CLI to generate and update Python unit tests automatically using coverage and AI
Author: Ofido
Project-URL: Homepage, https://github.com/ofido/AIUnitTest
Project-URL: Bug Tracker, https://github.com/ofido/AIUnitTest/issues
Keywords: testing,coverage,openai,automation
Classifier: Development Status :: 3 - Alpha
Classifier: Intended Audience :: Developers
Classifier: Programming Language :: Python :: 3
Classifier: Programming Language :: Python :: 3.10
Classifier: Programming Language :: Python :: 3.11
Classifier: Programming Language :: Python :: 3.12
Classifier: Programming Language :: Python :: 3.13
Classifier: Topic :: Software Development :: Testing
Classifier: Topic :: Utilities
Requires-Python: >=3.10
License-File: LICENSE
Requires-Dist: openai==2.3.0
Requires-Dist: coverage==7.10.7
Requires-Dist: typer==0.19.2
Requires-Dist: tomli==2.3.0
Requires-Dist: typing-extensions==4.15.0
Provides-Extra: huggingface
Requires-Dist: sentence-transformers==5.1.1; extra == "huggingface"
Requires-Dist: huggingface-hub==0.35.3; extra == "huggingface"
Provides-Extra: faiss
Requires-Dist: faiss-cpu==1.12.0; extra == "faiss"
Requires-Dist: numpy==2.3.3; extra == "faiss"
Requires-Dist: scikit-learn==1.7.2; extra == "faiss"
Requires-Dist: joblib==1.5.2; extra == "faiss"
Provides-Extra: all
Requires-Dist: sentence-transformers==5.1.1; extra == "all"
Requires-Dist: huggingface-hub==0.35.3; extra == "all"
Requires-Dist: faiss-cpu==1.12.0; extra == "all"
Requires-Dist: numpy==2.3.3; extra == "all"
Requires-Dist: scikit-learn==1.7.2; extra == "all"
Requires-Dist: joblib==1.5.2; extra == "all"
Requires-Dist: psutil==7.1.0; extra == "all"
Provides-Extra: dev
Requires-Dist: black==25.9.0; extra == "dev"
Requires-Dist: isort==7.0.0; extra == "dev"
Requires-Dist: flake8==7.3.0; extra == "dev"
Requires-Dist: flake8-bugbear==24.12.12; extra == "dev"
Requires-Dist: flake8-annotations==3.2.0; extra == "dev"
Requires-Dist: flake8-docstrings==1.7.0; extra == "dev"
Requires-Dist: flake8-comprehensions==3.17.0; extra == "dev"
Requires-Dist: flake8-eradicate==1.5.0; extra == "dev"
Requires-Dist: flake8-pytest-style==2.1.0; extra == "dev"
Requires-Dist: mypy==1.18.2; extra == "dev"
Requires-Dist: pre-commit==4.3.0; extra == "dev"
Requires-Dist: pytest==8.4.2; extra == "dev"
Requires-Dist: pytest-cov==7.0.0; extra == "dev"
Requires-Dist: pytest-asyncio==1.2.0; extra == "dev"
Requires-Dist: pytest-dotenv==0.5.2; extra == "dev"
Requires-Dist: joblib-stubs==1.5.2.0.20250831; extra == "dev"
Requires-Dist: types-psutil==7.0.0.20251001; extra == "dev"
Requires-Dist: pytest-mock==3.15.1; extra == "dev"
Requires-Dist: psutil==7.1.0; extra == "dev"
Dynamic: license-file
